mqp_client-0.1.5.dist-info/METADATA
mqp_client-0.1.5.dist-info/WHEEL
mqp_client-0.1.5.dist-info/entry_points.txt
mqp_client-0.1.5.dist-info/licenses/LICENSE
mqp_client/__init__.py
mqp_client/base_client.py
mqp_client/mqp_client.py
mqp_client/resource_info.py
mqp_client/settings.py
mqp_client-0.1.5.dist-info/RECORD
