Metadata-Version: 2.1
Name: mqp-client
Version: 0.1.5
Summary: A client for MQP
Author-Email: mqss <mqss@munich-quantum-valley.de>
License: Apache-2.0
Requires-Python: >=3.8
Requires-Dist: requests>=2.31.0
Requires-Dist: python-decouple>=3.8
Provides-Extra: dev
Requires-Dist: mypy>=1.10.1; extra == "dev"
Requires-Dist: pylint>=3.2.5; extra == "dev"
Requires-Dist: isort>=5.13.2; extra == "dev"
Requires-Dist: black>=24.4.2; extra == "dev"
Requires-Dist: pytest>=8.3.2; extra == "dev"
Requires-Dist: pre-commit>=3.3.1; extra == "dev"
Requires-Dist: nox>=2024.10.9; extra == "dev"
